<?xml version = '1.0'  encoding = 'ISO-8859-1'  standalone = 'yes' ?>
<!-- PlotDigitizer data file: created on Tue Mar 05 14:38:19 CET 2024 -->
<data>
<image file='figure-4.png' />
<axesnames x='year'  y='depth' />
<calibpoints minXaxisX='377.5' minXaxisY='287.5' maxXaxisX='649.0' maxXaxisY='289.0' minYaxisX='377.5' minYaxisY='287.5' maxYaxisX='378.5' maxYaxisY='45.5' aX1='1976.16666' aX2='1976.9166666' aY1='16.0' aY2='0.0' isXLog='false' isYLog='false' />
<point n='0' x='407.0' y='84.5' dx='1976.2450518137048' dy='2.568043284706527' />
<point n='1' x='406.0' y='144.0' dx='1976.2431975149868' dy='6.502203045453507' />
<point n='2' x='405.5' y='204.5' dx='1976.2427396634514' dy='10.502294363399768' />
<point n='3' x='405.5' y='266.0' dx='1976.243678259099' dy='14.568317238545303' />
<point n='4' x='439.5' y='88.0' dx='1976.3348822849337' dy='2.7875716275140965' />
<point n='5' x='439.0' y='147.5' dx='1976.3344091716806' dy='6.721548752368561' />
<point n='6' x='438.5' y='209.0' dx='1976.333966581863' dy='10.787754263406619' />
<point n='7' x='438.0' y='271.0' dx='1976.3335316229045' dy='14.887016870990577' />
<point n='8' x='450.0' y='88.5' dx='1976.3638948105547' dy='2.816793370317102' />
<point n='9' x='448.0' y='148.5' dx='1976.359285771766' dy='6.7843754993950185' />
<point n='10' x='447.0' y='210.0' dx='1976.3574619964836' dy='10.850763646325596' />
<point n='11' x='447.0' y='271.5' dx='1976.358400592131' dy='14.916786521471137' />
<point n='12' x='464.5' y='91.5' dx='1976.4039949741896' dy='3.009839508709449' />
<point n='13' x='465.5' y='151.5' dx='1976.40767304819' dy='6.976325822432255' />
<point n='14' x='465.0' y='212.5' dx='1976.4072228275136' dy='11.009474236924412' />
<point n='15' x='464.5' y='274.5' dx='1976.4067878685548' dy='15.108736844508373' />
<point n='16' x='486.5' y='87.0' dx='1976.4646984569133' dy='2.704289660525534' />
<point n='17' x='485.0' y='147.5' dx='1976.4614782344484' dy='6.704746250256832' />
<point n='18' x='485.5' y='208.5' dx='1976.4637903847017' dy='10.737529392963953' />
<point n='19' x='485.5' y='269.0' dx='1976.4647137186312' dy='14.73743807501769' />
<point n='20' x='500.5' y='76.5' dx='1976.5032114018923' dy='2.004976828071137' />
<point n='21' x='499.5' y='137.5' dx='1976.501379995751' dy='6.038307878455814' />
<point n='22' x='499.0' y='199.0' dx='1976.5009374059337' dy='10.10451338949387' />
<point n='23' x='499.5' y='260.5' dx='1976.5032571870458' dy='14.17035362874689' />
<point n='24' x='511.0' y='75.5' dx='1976.5322010349366' dy='1.9350272812364446' />
<point n='25' x='510.0' y='196.0' dx='1976.5312777010072' dy='9.902152820583066' />
<point n='26' x='549.0' y='71.0' dx='1976.6371024525363' dy='1.6236330844919307' />
<point n='27' x='548.5' y='131.5' dx='1976.636644601001' dy='5.6237244024381905' />
<point n='28' x='548.5' y='192.5' dx='1976.6375755657896' dy='9.65669018103783' />
<point n='29' x='549.0' y='265.57750120979506' dx='1976.6400720394586' dy='14.487967570795755' />
<point n='30' x='580.0' y='74.0' dx='1976.7227817365117' dy='1.8106522384311576' />
<point n='31' x='578.0' y='135.0' dx='1976.7181879594407' dy='5.8443485606008725' />
<point n='32' x='578.0' y='195.0' dx='1976.7191036625113' dy='9.811200146108716' />
<point n='33' x='579.5' y='256.0' dx='1976.7241781836944' dy='13.843618017030797' />
</data>
