<?xml version = '1.0'  encoding = 'ISO-8859-1'  standalone = 'yes' ?>
<!-- PlotDigitizer data file: created on Wed Jan 15 10:47:37 CET 2025 -->
<data>
<image file='figure-4.jpg' />
<axesnames x='temperature'  y='depth' />
<calibpoints minXaxisX='159.33333333333334' minXaxisY='621.3333333333334' maxXaxisX='516.0' maxXaxisY='621.3333333333334' minYaxisX='516.0' minYaxisY='621.3333333333334' maxYaxisX='515.3333333333334' maxYaxisY='32.0' aX1='-12.0' aX2='0.0' aY1='10.0' aY2='0.0' isXLog='false' isYLog='false' />
<point n='0' x='512.0' y='39.5' dx='-0.13457943925233806' dy='0.12726244343891402' />
<point n='1' x='486.5' y='66.0' dx='-0.992523364485983' dy='0.576923076923077' />
<point n='2' x='458.0' y='87.0' dx='-1.9514018691588806' dy='0.9332579185520361' />
<point n='3' x='419.5' y='113.5' dx='-3.246728971962618' dy='1.382918552036199' />
<point n='4' x='394.0' y='137.5' dx='-4.104672897196263' dy='1.7901583710407238' />
<point n='5' x='379.0' y='158.5' dx='-4.6093457943925245' dy='2.146493212669683' />
<point n='6' x='363.5' y='187.0' dx='-5.13084112149533' dy='2.6300904977375565' />
<point n='7' x='342.5' y='231.5' dx='-5.837383177570095' dy='3.385180995475113' />
<point n='8' x='332.0' y='249.5' dx='-6.190654205607478' dy='3.6906108597285066' />
<point n='9' x='325.5' y='267.0' dx='-6.409345794392525' dy='3.987556561085973' />
<point n='10' x='321.0' y='287.5' dx='-6.560747663551403' dy='4.335407239819005' />
<point n='11' x='316.0' y='333.0' dx='-6.728971962616825' dy='5.107466063348416' />
<point n='12' x='314.5' y='353.5' dx='-6.77943925233645' dy='5.455316742081448' />
<point n='13' x='311.5' y='381.0' dx='-6.880373831775703' dy='5.9219457013574655' />
<point n='14' x='300.0' y='425.5' dx='-7.26728971962617' dy='6.677036199095022' />
<point n='15' x='297.0' y='443.5' dx='-7.368224299065423' dy='6.982466063348416' />
<point n='16' x='292.5' y='471.5' dx='-7.519626168224301' dy='7.457579185520361' />
<point n='17' x='286.0' y='508.0' dx='-7.738317757009348' dy='8.076923076923077' />
<point n='18' x='282.0' y='525.5' dx='-7.872897196261684' dy='8.373868778280542' />
<point n='19' x='279.0' y='542.0' dx='-7.973831775700937' dy='8.653846153846153' />
<point n='20' x='279.5' y='564.5' dx='-7.957009345794395' dy='9.035633484162895' />
<point n='21' x='286.0' y='592.5' dx='-7.738317757009348' dy='9.510746606334841' />
</data>
